{
    "$schema": "http://json-schema.org/draft-07/schema",
    "$id": "http://example.com/example.json",
    "type": "array",
    "title": "The root schema",
    "description": "The root schema comprises the entire JSON document.",
    "default": [],
    "examples": [
        [
            {
                "used": false,
                "source": "user",
                "type": "cat",
                "deleted": false,
                "_id": "5d38bc630f1c57001592f151",
                "user": "5a9ac18c7478810ea6c06381",
                "text": "Georgia O'Keeffe was a celebrated painter, a figurehead of American modernism, a fashion icon, and... a cat owner! O'Keeffe kept a number of animals at her home in New Mexico, including her pet Siamese cat, who appears alongside O'Keeffe in a portrait shot by photographer John Candelario.",
                "createdAt": "2019-07-24T20:15:31.771Z",
                "updatedAt": "2020-08-23T20:20:01.611Z",
                "__v": 0,
                "status": {
                    "verified": true,
                    "sentCount": 1
                }
            }
        ]
    ],
    "additionalItems": true,
    "items": {
        "$id": "#/items",
        "anyOf": [
            {
                "$id": "#/items/anyOf/0",
                "type": "object",
                "title": "The first anyOf schema",
                "description": "An explanation about the purpose of this instance.",
                "default": {},
                "examples": [
                    {
                        "used": false,
                        "source": "user",
                        "type": "cat",
                        "deleted": false,
                        "_id": "5d38bc630f1c57001592f151",
                        "user": "5a9ac18c7478810ea6c06381",
                        "text": "Georgia O'Keeffe was a celebrated painter, a figurehead of American modernism, a fashion icon, and... a cat owner! O'Keeffe kept a number of animals at her home in New Mexico, including her pet Siamese cat, who appears alongside O'Keeffe in a portrait shot by photographer John Candelario.",
                        "createdAt": "2019-07-24T20:15:31.771Z",
                        "updatedAt": "2020-08-23T20:20:01.611Z",
                        "__v": 0,
                        "status": {
                            "verified": true,
                            "sentCount": 1
                        }
                    }
                ],
                "required": [
                    "used",
                    "source",
                    "type",
                    "deleted",
                    "_id",
                    "user",
                    "text",
                    "updatedAt"
                ],
                "properties": {
                    "used": {
                        "$id": "#/items/anyOf/0/properties/used",
                        "type": "boolean",
                        "title": "The used schema",
                        "description": "An explanation about the purpose of this instance.",
                        "default": false,
                        "examples": [
                            false
                        ]
                    },
                    "source": {
                        "$id": "#/items/anyOf/0/properties/source",
                        "type": "string",
                        "title": "The source schema",
                        "description": "An explanation about the purpose of this instance.",
                        "default": "",
                        "examples": [
                            "user"
                        ]
                    },
                    "type": {
                        "$id": "#/items/anyOf/0/properties/type",
                        "type": "string",
                        "title": "The type schema",
                        "description": "An explanation about the purpose of this instance.",
                        "default": "",
                        "examples": [
                            "cat"
                        ]
                    },
                    "deleted": {
                        "$id": "#/items/anyOf/0/properties/deleted",
                        "type": "boolean",
                        "title": "The deleted schema",
                        "description": "An explanation about the purpose of this instance.",
                        "default": false,
                        "examples": [
                            false
                        ]
                    },
                    "_id": {
                        "$id": "#/items/anyOf/0/properties/_id",
                        "type": "string",
                        "title": "The _id schema",
                        "description": "An explanation about the purpose of this instance.",
                        "default": "",
                        "examples": [
                            "5d38bc630f1c57001592f151"
                        ]
                    },
                    "user": {
                        "$id": "#/items/anyOf/0/properties/user",
                        "type": "string",
                        "title": "The user schema",
                        "description": "An explanation about the purpose of this instance.",
                        "default": "",
                        "examples": [
                            "5a9ac18c7478810ea6c06381"
                        ]
                    },
                    "text": {
                        "$id": "#/items/anyOf/0/properties/text",
                        "type": "string",
                        "title": "The text schema",
                        "description": "An explanation about the purpose of this instance.",
                        "default": "",
                        "examples": [
                            "Georgia O'Keeffe was a celebrated painter, a figurehead of American modernism, a fashion icon, and... a cat owner! O'Keeffe kept a number of animals at her home in New Mexico, including her pet Siamese cat, who appears alongside O'Keeffe in a portrait shot by photographer John Candelario."
                        ]
                    },
                    "createdAt": {
                        "$id": "#/items/anyOf/0/properties/createdAt",
                        "type": "string",
                        "title": "The createdAt schema",
                        "description": "An explanation about the purpose of this instance.",
                        "default": "",
                        "examples": [
                            "2019-07-24T20:15:31.771Z"
                        ]
                    },
                    "updatedAt": {
                        "$id": "#/items/anyOf/0/properties/updatedAt",
                        "type": "string",
                        "title": "The updatedAt schema",
                        "description": "An explanation about the purpose of this instance.",
                        "default": "",
                        "examples": [
                            "2020-08-23T20:20:01.611Z"
                        ]
                    },
                    "__v": {
                        "$id": "#/items/anyOf/0/properties/__v",
                        "type": "integer",
                        "title": "The __v schema",
                        "description": "An explanation about the purpose of this instance.",
                        "default": 0,
                        "examples": [
                            0
                        ]
                    },
                    "status": {
                        "$id": "#/items/anyOf/0/properties/status",
                        "type": "object",
                        "title": "The status schema",
                        "description": "An explanation about the purpose of this instance.",
                        "default": {},
                        "examples": [
                            {
                                "verified": true,
                                "sentCount": 1
                            }
                        ],
                        "required": [
                            "verified",
                            "sentCount"
                        ],
                        "properties": {
                            "verified": {
                                "$id": "#/items/anyOf/0/properties/status/properties/verified",
                                "type": "boolean",
                                "title": "The verified schema",
                                "description": "An explanation about the purpose of this instance.",
                                "default": false,
                                "examples": [
                                    true
                                ]
                            },
                            "sentCount": {
                                "$id": "#/items/anyOf/0/properties/status/properties/sentCount",
                                "type": "integer",
                                "title": "The sentCount schema",
                                "description": "An explanation about the purpose of this instance.",
                                "default": 0,
                                "examples": [
                                    1
                                ]
                            }
                        },
                        "additionalProperties": true
                    }
                },
                "additionalProperties": true
            }
        ]
    }
}